README.rst
setup.cfg
setup.py
mkbasicauth/__init__.py
mkbasicauth.egg-info/PKG-INFO
mkbasicauth.egg-info/SOURCES.txt
mkbasicauth.egg-info/dependency_links.txt
mkbasicauth.egg-info/entry_points.txt
mkbasicauth.egg-info/top_level.txt