Metadata-Version: 1.0
Name: mkbasicauth
Version: 0.0
Summary: Command to generate credential for Basic authentication
Home-page: UNKNOWN
Author: UNKNOWN
Author-email: UNKNOWN
License: UNKNOWN
Platform: UNKNOWN
